bids_stb/__init__.py
BIDS_stb-0.0.2.dist-info/LICENSE
BIDS_stb-0.0.2.dist-info/METADATA
BIDS_stb-0.0.2.dist-info/WHEEL
BIDS_stb-0.0.2.dist-info/entry_points.txt
BIDS_stb-0.0.2.dist-info/top_level.txt
BIDS_stb-0.0.2.dist-info/RECORD
