Metadata-Version: 2.1
Name: BIDS-stb
Version: 0.0.2
Summary: Small function to produce a set of single trial beta models from a BIDS compliant statistical model.
Home-page: https://github.com/nimh-comppsych/BIDS_stb
Author: Chris C. Camp
Author-email: chrisclaycamp@gmail.com
License: UNKNOWN
Platform: UNKNOWN
Classifier: Programming Language :: Python :: 3
Classifier: Operating System :: POSIX
Requires-Dist: Click
